LICENSE.MIT
README.md
linter_module.c
pyproject.toml
setup.cfg
setup.py
trojan_linter/__main__.py
trojan_linter/cli.py
trojan_linter/confusables.py
trojan_linter/linter.py
trojan_linter/nits.py
trojan_linter/profiles.py
trojan_linter/tokenize_python.py
trojan_linter.egg-info/PKG-INFO
trojan_linter.egg-info/SOURCES.txt
trojan_linter.egg-info/dependency_links.txt
trojan_linter.egg-info/not-zip-safe
trojan_linter.egg-info/requires.txt
trojan_linter.egg-info/top_level.txt