Metadata-Version: 2.1
Name: trojan-linter
Version: 0.0.1
Summary: Linter for reordered text, homoglyphs and control characters
Home-page: https://github.com/encukou/trojan_linter
License: MIT
Keywords: linter,trojan-source
Platform: UNKNOWN
Classifier: Framework :: Django
Classifier: License :: OSI Approved :: MIT License
Classifier: Programming Language :: Python :: 3
Provides-Extra: test
Provides-Extra: lint
License-File: LICENSE.MIT
